{
  "sections": {
    "16299683217c801bfb": {
      "type": "tbc-banner",
      "settings": {
        "content_alignment": "center",
        "image_1": "shopify:\/\/shop_images\/lady-header.png",
        "image_2": "shopify:\/\/shop_images\/bg-heather.jpg",
        "caption": "Physio, Active Rehab, Education, Products",
        "heading": "Fell better in <span>your body<\/span> with uniquely tailored movements.",
        "button_label": "Button Label",
        "button_link_1": "",
        "caption_color": "#ff6976",
        "heading_color": "#1c7ee3",
        "button_color": "#ff6976",
        "highlight_color": "#ec86d0",
        "highlight_text_color": "#ffffff"
      }
    },
    "163013949020d3b718": {
      "type": "tbc-ticker",
      "settings": {
        "image_1": "shopify:\/\/shop_images\/bgticker.png",
        "image_2": "shopify:\/\/shop_images\/TBC_webTextureBanner.jpg"
      }
    },
    "16301459394b558fdd": {
      "type": "tbc-info-block",
      "blocks": {
        "7c10a37f-d9b4-472e-8c52-f8258e9d216d": {
          "type": "info",
          "settings": {
            "icon": "https:\/\/cdn.shopify.com\/s\/files\/1\/0577\/0844\/5857\/files\/Trauma.svg?v=1630150742",
            "heading": "Trauma Informed Team",
            "content": "Our team understands how to navigate and respect your unique history while creating the most sensitive and appropriate plan for you."
          }
        },
        "baf78fe2-e609-4c0e-9e39-91d2f8e77f44": {
          "type": "info",
          "settings": {
            "icon": "https:\/\/cdn.shopify.com\/s\/files\/1\/0577\/0844\/5857\/files\/icon-committed.svg?v=1630643251",
            "heading": "Committed to Quality",
            "content": "We’re committed to continuously improving and learning so you’ll always be given the highest quality services and products."
          }
        },
        "0a8c1acc-c4f0-4f80-a910-4110af3c508a": {
          "type": "info",
          "settings": {
            "icon": "https:\/\/cdn.shopify.com\/s\/files\/1\/0577\/0844\/5857\/files\/icon-local_a86ef42c-804a-4acc-92e0-3fa95c1abbd6.svg?v=1630645415",
            "heading": "Local + Female Owned",
            "content": "Lorem Did you know we’re a female owned business based in North Vancouver, British Columbia? Oh chyea!"
          }
        },
        "6b170b5e-5251-4b24-aa03-45dfe93b1efe": {
          "type": "info",
          "settings": {
            "icon": "https:\/\/cdn.shopify.com\/s\/files\/1\/0577\/0844\/5857\/files\/positive-healf.svg?v=1630645244",
            "heading": "Environment Friendly",
            "content": "We’re committed to reducing harm to the environment and creating a positive impact on climate change."
          }
        }
      },
      "block_order": [
        "7c10a37f-d9b4-472e-8c52-f8258e9d216d",
        "baf78fe2-e609-4c0e-9e39-91d2f8e77f44",
        "0a8c1acc-c4f0-4f80-a910-4110af3c508a",
        "6b170b5e-5251-4b24-aa03-45dfe93b1efe"
      ],
      "settings": {
        "direction": false,
        "fancy": false,
        "image_1": "shopify:\/\/shop_images\/what-we-are-section.png",
        "title": "What we’re all about",
        "title_colour": "#1c7ee3",
        "text_colour": "#262c96"
      }
    },
    "featured_products": {
      "type": "featured-collection",
      "settings": {
        "title": "Products",
        "bg_image": "shopify:\/\/shop_images\/bg-heather_f9ee17aa-93b1-4220-9c97-65b1ea122996.jpg",
        "collection": "all",
        "products_to_show": 4,
        "show_view_all": true,
        "swipe_on_mobile": false,
        "image_ratio": "square",
        "show_secondary_image": false,
        "add_image_padding": false,
        "show_image_outline": false,
        "show_vendor": false
      }
    },
    "1630199682ccd2f15a": {
      "type": "tbc-text-banner",
      "settings": {
        "bg_image": "shopify:\/\/shop_images\/blue-bg.jpg",
        "contained": false,
        "container_color": "#ffffff",
        "caption": "SERVICES",
        "content": "Go live that kick-ass life. We’re here to support your body.",
        "button_label": "Learn More",
        "button_link_1": "shopify:\/\/pages\/our-services",
        "caption_color": "#ffc600",
        "content_color": "#ffffff",
        "button_color": "#ff6976"
      }
    },
    "16302161411f026622": {
      "type": "tbc-slider-testimonial",
      "blocks": {
        "16302161411f026622-0": {
          "type": "testimonial",
          "settings": {
            "content": "One session in and my mobility and comfort have already improved. The technique is different from anything I personally have experienced, but it works! Danielle talked me through every step of treatment.",
            "name": "Sam S."
          }
        },
        "16302161411f026622-1": {
          "type": "testimonial",
          "settings": {
            "content": "Danielle is very thorough in her assessments.   Her upbeat and straightforward personality is beneficial in understanding key components of your injury and exercises which will increase your success in healing.",
            "name": "Susan R."
          }
        },
        "16302161411f026622-2": {
          "type": "testimonial",
          "settings": {
            "content": "I’ve been seeing Danielle for over a year now for multiple injuries. I’m always amazed by the results I get with her. She is extremely talented at what she does.",
            "name": "Wes S."
          }
        },
        "16302161411f026622-3": {
          "type": "testimonial",
          "settings": {
            "content": "Just wonderful! Truly, always an amazing experience receiving your treatments and I will never get over the feeling of walking out of your office feeling so different to when I walked in!",
            "name": "Mioara M."
          }
        }
      },
      "block_order": [
        "16302161411f026622-0",
        "16302161411f026622-1",
        "16302161411f026622-2",
        "16302161411f026622-3"
      ],
      "settings": {
        "section_title": "Testimonials"
      }
    },
    "1630221088c6b6c9b7": {
      "type": "tbc-multibanner",
      "blocks": {
        "1630221088c6b6c9b7-0": {
          "type": "banner",
          "settings": {
            "image_1": "shopify:\/\/shop_images\/Group_554.jpg",
            "caption": "EVENTS & EDUCATION",
            "title": "Come learn, heal and Laugh with us.",
            "button_label": "JOIN US",
            "button_url": "shopify:\/\/blogs\/events"
          }
        },
        "1630221088c6b6c9b7-1": {
          "type": "banner",
          "settings": {
            "image_1": "shopify:\/\/shop_images\/Group_555.jpg",
            "caption": "BLOGS",
            "title": "Wellness tips for a balanced life.",
            "button_label": "READ MORE",
            "button_url": "shopify:\/\/blogs\/news"
          }
        }
      },
      "block_order": [
        "1630221088c6b6c9b7-0",
        "1630221088c6b6c9b7-1"
      ],
      "settings": {
        "section_title": ""
      }
    },
    "16307000205bfa80d1": {
      "type": "tbc-custom-newsletter",
      "settings": {
        "bg_image": "shopify:\/\/shop_images\/TBC_webTextureBanner.jpg",
        "heading": "Stay up to date on health tips,\nevents and new products!",
        "button_label": "Button Label",
        "heading_color": "#ffffff"
      }
    }
  },
  "order": [
    "16299683217c801bfb",
    "163013949020d3b718",
    "16301459394b558fdd",
    "featured_products",
    "1630199682ccd2f15a",
    "16302161411f026622",
    "1630221088c6b6c9b7",
    "16307000205bfa80d1"
  ]
}
